calculadora_imc_1310/__init__.py
calculadora_imc_1310/calcular_imc.py
calculadora_imc_1310-0.0.1.dist-info/METADATA
calculadora_imc_1310-0.0.1.dist-info/WHEEL
calculadora_imc_1310-0.0.1.dist-info/top_level.txt
calculadora_imc_1310-0.0.1.dist-info/RECORD
