Metadata-Version: 2.1
Name: calculadora_imc_1310
Version: 0.0.1
Summary: Calculadaor de IMC (Índice de Massa Corporal)
Home-page: https://github.com/SergioMCavalcante/calculadora_imc_1310
Author: SMC
Requires-Python: >=3.8
